odoo/addons/payroll_contract_advantages/README.rst
odoo/addons/payroll_contract_advantages/__init__.py
odoo/addons/payroll_contract_advantages/__manifest__.py
odoo/addons/payroll_contract_advantages/i18n/es.po
odoo/addons/payroll_contract_advantages/i18n/es_AR.po
odoo/addons/payroll_contract_advantages/i18n/payroll_contract_advantages.pot
odoo/addons/payroll_contract_advantages/models/__init__.py
odoo/addons/payroll_contract_advantages/models/hr_contract.py
odoo/addons/payroll_contract_advantages/models/hr_contract_advantage.py
odoo/addons/payroll_contract_advantages/models/hr_contract_advantage_template.py
odoo/addons/payroll_contract_advantages/models/hr_payslip.py
odoo/addons/payroll_contract_advantages/readme/CONTRIBUTORS.rst
odoo/addons/payroll_contract_advantages/readme/DESCRIPTION.rst
odoo/addons/payroll_contract_advantages/readme/USAGE.rst
odoo/addons/payroll_contract_advantages/security/ir.model.access.csv
odoo/addons/payroll_contract_advantages/static/description/icon.png
odoo/addons/payroll_contract_advantages/static/description/index.html
odoo/addons/payroll_contract_advantages/views/hr_contract_advantage_views.xml
odoo/addons/payroll_contract_advantages/views/hr_contract_views.xml
odoo14_addon_payroll_contract_advantages-14.0.3.0.0.dist-info/METADATA
odoo14_addon_payroll_contract_advantages-14.0.3.0.0.dist-info/WHEEL
odoo14_addon_payroll_contract_advantages-14.0.3.0.0.dist-info/top_level.txt
odoo14_addon_payroll_contract_advantages-14.0.3.0.0.dist-info/RECORD
