Metadata-Version: 2.1
Name: odoo14-addon-payroll-contract-advantages
Version: 14.0.3.0.0
Summary: Allow to define contract advantages for employees.
Home-page: https://github.com/OCA/payroll
Author: Nimarosa, Odoo Community Association (OCA)
Author-email: support@odoo-community.org
License: LGPL-3
Platform: UNKNOWN
Classifier: Programming Language :: Python
Classifier: Framework :: Odoo
Classifier: Framework :: Odoo :: 14.0
Classifier: License :: OSI Approved :: GNU Lesser General Public License v3 (LGPLv3)
Requires-Python: >=3.6
Requires-Dist: odoo14-addon-payroll
Requires-Dist: odoo (<14.1dev,>=14.0a)
